pylogsentinel/__init__.py
pylogsentinel/__main__.py
pylogsentinel/core.py
pylogsentinel-0.3.0.dist-info/licenses/LICENSE
pylogsentinel-0.3.0.dist-info/METADATA
pylogsentinel-0.3.0.dist-info/WHEEL
pylogsentinel-0.3.0.dist-info/top_level.txt
pylogsentinel-0.3.0.dist-info/RECORD
