Metadata-Version: 2.4
Name: pylogsentinel
Version: 0.3.0
Summary: Lightweight cron-friendly log monitoring utility with regex rules and per-rule shell actions
Author-email: Jan Tuomi <jan@jantuomi.fi>
License-Expression: MIT
Project-URL: Homepage, https://github.com/jantuomi/pylogsentinel
Project-URL: Repository, https://github.com/jantuomi/pylogsentinel.git
Project-URL: Issues, https://github.com/jantuomi/pylogsentinel/issues
Keywords: log,monitoring,regex,cron,alerting,sentinel
Requires-Python: >=3.9
License-File: LICENSE
Dynamic: license-file
